[
   {
      "rom": "ZirconiumAosp",
      "rom_tag": "Aoszp",
      "build_type": "official",
      "version": "IGNITE",
      "build_date": "(2019/03/16)",
      "image": "images/Z.jpg",
      "device": "Yu Yuphoria",
      "codename": "LETTUCE",
      "thread_link": "https://forum.xda-developers.com/showpost.php?p=79130252&postcount=5",
      "download_link": "https://sourceforge.net/projects/zirconiumaosp/files/lettuce/ZirconiumAosp-9.0-IGNITE-lettuce-20190316-0915-OFFICIAL.zip/download",
      "developer_name": "Yasir siddiqui",
      "developer_contact": "https://t.me/Yasirsiddiqui",
      "changelog": "changelog.txt",
      "group_link": "https://t.me/ZirconiumAospChat"
   }
]

